app/__init__.py
app/__main__.py
app/application.py
app/email_validator.py
email_validaor-1.0.1.dist-info/METADATA
email_validaor-1.0.1.dist-info/WHEEL
email_validaor-1.0.1.dist-info/entry_points.txt
email_validaor-1.0.1.dist-info/top_level.txt
email_validaor-1.0.1.dist-info/RECORD
